jux/__init__.py
jux/actions.py
jux/config.py
jux/env.py
jux/factory.py
jux/team.py
jux/torch.py
jux/tree_util.py
jux/unit.py
jux/unit_cargo.py
jux/weather.py
jux/map/__init__.py
jux/map/board.py
jux/map/position.py
jux/map_generator/__init__.py
jux/map_generator/flood.py
jux/map_generator/generator.py
jux/map_generator/simplexnoise.py
jux/map_generator/symnoise.py
jux/state/__init__.py
jux/state/state.py
jux/utils/__init__.py
juxai2022-1.0.dist-info/LICENSE
juxai2022-1.0.dist-info/METADATA
juxai2022-1.0.dist-info/WHEEL
juxai2022-1.0.dist-info/top_level.txt
juxai2022-1.0.dist-info/RECORD
