Metadata-Version: 2.1
Name: juxai2022
Version: 1.0
Summary: JUX is a jax-accelerated engine for Lux-2022.
Author-email: Qimai Li <qimaili@chaocanshu.ai>, Yuhao Jiang <yuhaojiang@chaocanshu.ai>
License: MIT License
Project-URL: repository, https://github.com/RoboEden/jux
Project-URL: Bug Tracker, https://github.com/RoboEden/jux/issues
Keywords: JAX,LuxAI2022
Classifier: Programming Language :: Python :: 3
Classifier: Environment :: GPU :: NVIDIA CUDA
Classifier: License :: OSI Approved :: MIT License
Classifier: Topic :: Games/Entertainment :: Real Time Strategy
Classifier: Topic :: Scientific/Engineering :: Artificial Intelligence
Requires-Python: <3.11,>=3.7
License-File: LICENSE
Requires-Dist: luxai2022 (==1.1.4)
Requires-Dist: jax[cuda] (~=0.3.25)
Requires-Dist: chex
Provides-Extra: dev
Requires-Dist: toml ; extra == 'dev'
Requires-Dist: pre-commit ; extra == 'dev'
Requires-Dist: pytype ; extra == 'dev'
Requires-Dist: tox ; extra == 'dev'
Requires-Dist: tox-conda ; extra == 'dev'
Requires-Dist: pytest ; extra == 'dev'
Requires-Dist: pytest-cov ; extra == 'dev'
Requires-Dist: isort ; extra == 'dev'
Requires-Dist: autoflake ; extra == 'dev'
Requires-Dist: yapf ; extra == 'dev'
Requires-Dist: bump2version ; extra == 'dev'
Requires-Dist: rich ; extra == 'dev'
Requires-Dist: pandas ; extra == 'dev'
Requires-Dist: ipywidgets (<8.0,>=7.0) ; extra == 'dev'
Requires-Dist: notebook ; extra == 'dev'
Requires-Dist: build ; extra == 'dev'
Requires-Dist: twine ; extra == 'dev'
Provides-Extra: torch
Requires-Dist: torch ; extra == 'torch'
Requires-Dist: torchvision ; extra == 'torch'
Requires-Dist: torchaudio ; extra == 'torch'
